greentext/__init__.py
greentext/media/__init__.py
greentext/media/dimensions.py
greentext/media/exceptions.py
greentext/media/thumbnails.py
greentext/posts/__init__.py
greentext/posts/catalog.py
greentext/posts/replies.py
greentext/posts/threads.py
greentext/users/__init__.py
greentext/users/countries.py
greentext-2019.11.5.dist-info/LICENSE
greentext-2019.11.5.dist-info/METADATA
greentext-2019.11.5.dist-info/WHEEL
greentext-2019.11.5.dist-info/top_level.txt
greentext-2019.11.5.dist-info/RECORD
